darwin_ml/__init__.py
darwin_ml/main.py
darwin_ml/test_setup.py
darwin_ml/handlers/__init__.py
darwin_ml/handlers/abstracts.py
darwin_ml/handlers/allocation.py
darwin_ml/handlers/base.py
darwin_ml/handlers/incremental.py
darwin_ml/handlers/incremental_engine.py
darwin_ml/handlers/state.py
darwin_ml/handlers/technical.py
darwin_ml/middleware/__init__.py
darwin_ml/middleware/containers/__init__.py
darwin_ml/middleware/containers/allocations.py
darwin_ml/middleware/containers/features.py
darwin_ml/middleware/containers/price.py
darwin_ml/middleware/containers/step.py
darwin_ml/middleware/procedures/__init__.py
darwin_ml/middleware/procedures/core.py
darwin_ml/middleware/procedures/management/__init__.py
darwin_ml/middleware/procedures/management/models.py
darwin_ml/middleware/procedures/models/__init__.py
darwin_ml/middleware/procedures/models/_creme.py
darwin_ml/middleware/procedures/models/_flow.py
darwin_ml/middleware/procedures/models/_sklearn.py
darwin_ml/middleware/procedures/models/_torch.py
darwin_ml/models/__init__.py
darwin_ml/models/allocation.py
darwin_ml/models/metadata.py
darwin_ml/models/online.py
darwin_ml/models/prediction.py
darwin_ml/models/pricing.py
darwin_ml/models/statespace.py
darwin_ml/models/creme_ml/__init__.py
darwin_ml/models/creme_ml/pipelines/__init__.py
darwin_ml/models/creme_ml/pipelines/hardened_classifier.py
darwin_ml/models/creme_ml/pipelines/pct_regressor.py
darwin_ml/models/creme_ml/transforms/__init__.py
darwin_ml/models/creme_ml/transforms/feature_change.py
darwin_ml/models/creme_ml/transforms/pct_change.py
darwin_ml/models/creme_ml/transforms/prediction_history.py
darwin_ml/params/__init__.py
darwin_ml/params/environment.py
darwin_ml/params/tests/__init__.py
darwin_ml/params/tests/price_related.py
darwin_ml/technical/__init__.py
darwin_ml/technical/core.py
darwin_ml/technical/momentum.py
darwin_ml/technical/signals.py
darwin_ml/technical/temp.py
darwin_ml/technical/trend.py
darwin_ml/technical/volume.py
darwin_ml-0.0.3.dist-info/METADATA
darwin_ml-0.0.3.dist-info/WHEEL
darwin_ml-0.0.3.dist-info/top_level.txt
darwin_ml-0.0.3.dist-info/RECORD
