Metadata-Version: 2.1
Name: darwin-ml
Version: 0.0.3
Summary: A wrapper for all online learning machine learning management. Periodic pickling in real-time.
Home-page: UNKNOWN
Author: Kevin Hill
Author-email: kah.kevin.hill@gmail.com
License: UNKNOWN
Platform: UNKNOWN
Classifier: Programming Language :: Python :: 3
Classifier: License :: OSI Approved :: MIT License
Classifier: Operating System :: OS Independent
Requires-Dist: jamboree
Requires-Dist: creme
